<root><image frameTop="0" rows="1" frameWidth="3" columnsAndRows="1" name="Tile_PirateCove0000" centrePointX="0" centrePointY="0" frameLeft="0" frameHeight="3" columns="1"/><image frameTop="3" rows="1" frameWidth="102" columnsAndRows="1" name="Tile_PirateCove0001" centrePointX="0" centrePointY="0" frameLeft="0" frameHeight="102" columns="1"/><image frameTop="105" rows="1" frameWidth="102" columnsAndRows="1" name="Tile_PirateCove0002" centrePointX="0" centrePointY="0" frameLeft="0" frameHeight="102" columns="1"/><image frameTop="207" rows="1" frameWidth="102" columnsAndRows="1" name="Tile_PirateCove0003" centrePointX="0" centrePointY="0" frameLeft="0" frameHeight="102" columns="1"/><image frameTop="309" rows="1" frameWidth="102" columnsAndRows="1" name="Tile_PirateCove0004" centrePointX="0" centrePointY="0" frameLeft="0" frameHeight="102" columns="1"/><image frameTop="411" rows="1" frameWidth="102" columnsAndRows="1" name="Tile_PirateCove0005" centrePointX="0" centrePointY="0" frameLeft="0" frameHeight="102" columns="1"/><image frameTop="513" rows="1" frameWidth="102" columnsAndRows="1" name="Tile_PirateCove0006" centrePointX="0" centrePointY="0" frameLeft="0" frameHeight="102" columns="1"/><image frameTop="615" rows="1" frameWidth="102" columnsAndRows="1" name="Tile_PirateCove0007" centrePointX="0" centrePointY="0" frameLeft="0" frameHeight="102" columns="1"/><image frameTop="717" rows="1" frameWidth="102" columnsAndRows="1" name="Tile_PirateCove0008" centrePointX="0" centrePointY="0" frameLeft="0" frameHeight="102" columns="1"/><image frameTop="819" rows="1" frameWidth="102" columnsAndRows="1" name="Tile_PirateCove0009" centrePointX="0" centrePointY="0" frameLeft="0" frameHeight="102" columns="1"/><image frameTop="921" rows="1" frameWidth="102" columnsAndRows="1" name="Tile_PirateCove0010" centrePointX="0" centrePointY="0" frameLeft="0" frameHeight="102" columns="1"/><image frameTop="1023" rows="1" frameWidth="102" columnsAndRows="1" name="Tile_PirateCove0011" centrePointX="0" centrePointY="0" frameLeft="0" frameHeight="102" columns="1"/><image frameTop="1125" rows="1" frameWidth="102" columnsAndRows="1" name="Tile_PirateCove0012" centrePointX="0" centrePointY="0" frameLeft="0" frameHeight="102" columns="1"/><image frameTop="1227" rows="1" frameWidth="102" columnsAndRows="1" name="Tile_PirateCove0013" centrePointX="0" centrePointY="0" frameLeft="0" frameHeight="102" columns="1"/><image frameTop="1329" rows="1" frameWidth="102" columnsAndRows="1" name="Tile_PirateCove0014" centrePointX="0" centrePointY="0" frameLeft="0" frameHeight="102" columns="1"/><image frameTop="1431" rows="1" frameWidth="102" columnsAndRows="1" name="Tile_PirateCove0015" centrePointX="0" centrePointY="0" frameLeft="0" frameHeight="102" columns="1"/><image frameTop="1533" rows="1" frameWidth="102" columnsAndRows="1" name="Tile_PirateCove0016" centrePointX="0" centrePointY="0" frameLeft="0" frameHeight="102" columns="1"/><image frameTop="1635" rows="1" frameWidth="102" columnsAndRows="1" name="Tile_PirateCove0017" centrePointX="0" centrePointY="0" frameLeft="0" frameHeight="102" columns="1"/><image frameTop="1737" rows="1" frameWidth="102" columnsAndRows="1" name="Tile_PirateCove0018" centrePointX="0" centrePointY="0" frameLeft="0" frameHeight="102" columns="1"/><image frameTop="1839" rows="1" frameWidth="102" columnsAndRows="1" name="Tile_PirateCove0019" centrePointX="0" centrePointY="0" frameLeft="0" frameHeight="102" columns="1"/><image frameTop="1941" rows="1" frameWidth="102" columnsAndRows="1" name="Tile_PirateCove0020" centrePointX="0" centrePointY="0" frameLeft="0" frameHeight="102" columns="1"/><image frameTop="0" rows="1" frameWidth="102" columnsAndRows="1" name="Tile_PirateCove0021" centrePointX="0" centrePointY="0" frameLeft="102" frameHeight="102" columns="1"/><image frameTop="0" rows="1" frameWidth="102" columnsAndRows="1" name="Tile_PirateCove0022" centrePointX="0" centrePointY="0" frameLeft="204" frameHeight="102" columns="1"/><image frameTop="0" rows="1" frameWidth="102" columnsAndRows="1" name="Tile_PirateCove0023" centrePointX="0" centrePointY="0" frameLeft="306" frameHeight="102" columns="1"/><image frameTop="0" rows="1" frameWidth="102" columnsAndRows="1" name="Tile_PirateCove0024" centrePointX="0" centrePointY="0" frameLeft="408" frameHeight="102" columns="1"/><image frameTop="0" rows="1" frameWidth="84" columnsAndRows="1" name="Tile_Slime" centrePointX="0" centrePointY="0" frameLeft="510" frameHeight="84" columns="1"/><image frameTop="0" rows="1" frameWidth="82" columnsAndRows="1" name="Tile_Water" centrePointX="0" centrePointY="0" frameLeft="594" frameHeight="82" columns="1"/><image frameTop="0" rows="1" frameWidth="82" columnsAndRows="1" name="Tile_Water_Top" centrePointX="0" centrePointY="0" frameLeft="676" frameHeight="82" columns="1"/><image frameTop="0" rows="1" frameWidth="77" columnsAndRows="1" name="remove_scenery_10" centrePointX="38.5" centrePointY="88" frameLeft="758" frameHeight="88" columns="1"/><image frameTop="0" rows="1" frameWidth="524" columnsAndRows="1" name="scenery_0" centrePointX="262" centrePointY="867" frameLeft="835" frameHeight="867" columns="1"/><image frameTop="88" rows="1" frameWidth="254" columnsAndRows="1" name="scenery_11" centrePointX="127" centrePointY="145" frameLeft="510" frameHeight="145" columns="1"/><image frameTop="102" rows="1" frameWidth="301" columnsAndRows="1" name="scenery_12" centrePointX="150.5" centrePointY="569" frameLeft="102" frameHeight="569" columns="1"/><image frameTop="233" rows="1" frameWidth="301" columnsAndRows="1" name="scenery_12_front" centrePointX="150.5" centrePointY="569" frameLeft="403" frameHeight="569" columns="1"/><image frameTop="102" rows="1" frameWidth="95" columnsAndRows="1" name="scenery_13" centrePointX="47.5" centrePointY="87" frameLeft="403" frameHeight="87" columns="1"/><image frameTop="802" rows="1" frameWidth="319" columnsAndRows="1" name="scenery_14" centrePointX="159.5" centrePointY="211" frameLeft="102" frameHeight="211" columns="1"/><image frameTop="802" rows="1" frameWidth="155" columnsAndRows="1" name="scenery_15" centrePointX="77.5" centrePointY="176" frameLeft="421" frameHeight="176" columns="1"/><image frameTop="671" rows="1" frameWidth="78" columnsAndRows="1" name="scenery_16" centrePointX="39" centrePointY="85" frameLeft="102" frameHeight="85" columns="1"/><image frameTop="0" rows="1" frameWidth="392" columnsAndRows="1" name="scenery_17" centrePointX="196" centrePointY="392" frameLeft="1359" frameHeight="392" columns="1"/><image frameTop="392" rows="1" frameWidth="392" columnsAndRows="1" name="scenery_18" centrePointX="196" centrePointY="392" frameLeft="1359" frameHeight="392" columns="1"/><image frameTop="671" rows="1" frameWidth="219" columnsAndRows="1" name="scenery_19" centrePointX="109.5" centrePointY="76" frameLeft="180" frameHeight="76" columns="1"/><image frameTop="802" rows="1" frameWidth="242" columnsAndRows="1" name="scenery_2" centrePointX="121" centrePointY="202" frameLeft="576" frameHeight="202" columns="1"/><image frameTop="233" rows="1" frameWidth="101" columnsAndRows="1" name="scenery_20" centrePointX="50.5" centrePointY="96" frameLeft="704" frameHeight="96" columns="1"/><image frameTop="189" rows="1" frameWidth="23" columnsAndRows="1" name="scenery_21" centrePointX="11.5" centrePointY="17" frameLeft="403" frameHeight="17" columns="1"/><image frameTop="747" rows="1" frameWidth="85" columnsAndRows="1" name="scenery_22" centrePointX="42.5" centrePointY="53" frameLeft="180" frameHeight="53" columns="1"/><image frameTop="329" rows="1" frameWidth="88" columnsAndRows="1" name="scenery_23" centrePointX="44" centrePointY="100" frameLeft="704" frameHeight="100" columns="1"/><image frameTop="429" rows="1" frameWidth="88" columnsAndRows="1" name="scenery_24" centrePointX="44" centrePointY="118" frameLeft="704" frameHeight="118" columns="1"/><image frameTop="547" rows="1" frameWidth="71" columnsAndRows="1" name="scenery_25" centrePointX="35.5" centrePointY="177" frameLeft="704" frameHeight="177" columns="1"/><image frameTop="0" rows="1" frameWidth="167" columnsAndRows="1" name="scenery_26" centrePointX="83.5" centrePointY="160" frameLeft="1751" frameHeight="160" columns="1"/><image frameTop="978" rows="1" frameWidth="121" columnsAndRows="1" name="scenery_27" centrePointX="60.5" centrePointY="229" frameLeft="421" frameHeight="229" columns="1"/><image frameTop="0" rows="1" frameWidth="92" columnsAndRows="1" name="scenery_28" centrePointX="46" centrePointY="92" frameLeft="1918" frameHeight="92" columns="1"/><image frameTop="92" rows="1" frameWidth="95" columnsAndRows="1" name="scenery_29" centrePointX="47.5" centrePointY="87" frameLeft="1918" frameHeight="87" columns="1"/><image frameTop="160" rows="1" frameWidth="93" columnsAndRows="1" name="scenery_3" centrePointX="46.5" centrePointY="87" frameLeft="1751" frameHeight="87" columns="1"/><image frameTop="756" rows="1" frameWidth="45" columnsAndRows="1" name="scenery_30" centrePointX="22.5" centrePointY="40" frameLeft="102" frameHeight="40" columns="1"/><image frameTop="1013" rows="1" frameWidth="82" columnsAndRows="1" name="scenery_31" centrePointX="41" centrePointY="117" frameLeft="102" frameHeight="117" columns="1"/><image frameTop="1013" rows="1" frameWidth="194" columnsAndRows="1" name="scenery_32" centrePointX="97" centrePointY="58" frameLeft="184" frameHeight="58" columns="1"/><image frameTop="784" rows="1" frameWidth="392" columnsAndRows="1" name="scenery_33" centrePointX="196" centrePointY="392" frameLeft="1359" frameHeight="392" columns="1"/><image frameTop="1130" rows="1" frameWidth="245" columnsAndRows="1" name="scenery_34" centrePointX="122.5" centrePointY="112" frameLeft="102" frameHeight="112" columns="1"/><image frameTop="179" rows="1" frameWidth="103" columnsAndRows="1" name="scenery_35" centrePointX="51.5" centrePointY="79" frameLeft="1844" frameHeight="79" columns="1"/><image frameTop="724" rows="1" frameWidth="90" columnsAndRows="1" name="scenery_36" centrePointX="45" centrePointY="75" frameLeft="704" frameHeight="75" columns="1"/><image frameTop="247" rows="1" frameWidth="78" columnsAndRows="1" name="scenery_37" centrePointX="39" centrePointY="85" frameLeft="1751" frameHeight="85" columns="1"/><image frameTop="867" rows="1" frameWidth="330" columnsAndRows="1" name="scenery_38" centrePointX="165" centrePointY="479" frameLeft="818" frameHeight="479" columns="1"/><image frameTop="867" rows="1" frameWidth="102" columnsAndRows="1" name="scenery_39" centrePointX="51" centrePointY="107" frameLeft="1148" frameHeight="107" columns="1"/><image frameTop="974" rows="1" frameWidth="112" columnsAndRows="1" name="scenery_4" centrePointX="56" centrePointY="75" frameLeft="1148" frameHeight="75" columns="1"/><image frameTop="756" rows="1" frameWidth="23" columnsAndRows="1" name="scenery_40" centrePointX="11.5" centrePointY="36" frameLeft="147" frameHeight="36" columns="1"/><image frameTop="1004" rows="1" frameWidth="233" columnsAndRows="1" name="scenery_42" centrePointX="116.5" centrePointY="219" frameLeft="542" frameHeight="219" columns="1"/><image frameTop="1049" rows="1" frameWidth="201" columnsAndRows="1" name="scenery_45" centrePointX="100.5" centrePointY="167" frameLeft="1148" frameHeight="167" columns="1"/><image frameTop="88" rows="1" frameWidth="69" columnsAndRows="1" name="scenery_49" centrePointX="34.5" centrePointY="65" frameLeft="764" frameHeight="65" columns="1"/><image frameTop="189" rows="1" frameWidth="65" columnsAndRows="1" name="scenery_5" centrePointX="32.5" centrePointY="42" frameLeft="426" frameHeight="42" columns="1"/><image frameTop="867" rows="1" frameWidth="99" columnsAndRows="1" name="scenery_52" centrePointX="49.5" centrePointY="83" frameLeft="1250" frameHeight="83" columns="1"/><image frameTop="153" rows="1" frameWidth="58" columnsAndRows="1" name="scenery_53" centrePointX="29" centrePointY="41" frameLeft="764" frameHeight="41" columns="1"/><image frameTop="1207" rows="1" frameWidth="93" columnsAndRows="1" name="scenery_55" centrePointX="46.5" centrePointY="602" frameLeft="347" frameHeight="602" columns="1"/><image frameTop="1207" rows="1" frameWidth="91" columnsAndRows="1" name="scenery_56" centrePointX="45.5" centrePointY="352" frameLeft="440" frameHeight="352" columns="1"/><image frameTop="329" rows="1" frameWidth="37" columnsAndRows="1" name="scenery_57" centrePointX="18.5" centrePointY="328" frameLeft="792" frameHeight="328" columns="1"/><image frameTop="1242" rows="1" frameWidth="199" columnsAndRows="1" name="scenery_6" centrePointX="99.5" centrePointY="190" frameLeft="102" frameHeight="190" columns="1"/><image frameTop="1223" rows="1" frameWidth="281" columnsAndRows="1" name="scenery_60" centrePointX="140.5" centrePointY="86" frameLeft="531" frameHeight="86" columns="1"/><image frameTop="1432" rows="1" frameWidth="173" columnsAndRows="1" name="scenery_61" centrePointX="86.5" centrePointY="175" frameLeft="102" frameHeight="175" columns="1"/><image frameTop="1309" rows="1" frameWidth="254" columnsAndRows="1" name="scenery_62" centrePointX="127" centrePointY="71" frameLeft="531" frameHeight="71" columns="1"/><image frameTop="1607" rows="1" frameWidth="169" columnsAndRows="1" name="scenery_63" centrePointX="84.5" centrePointY="133" frameLeft="102" frameHeight="133" columns="1"/><image frameTop="1809" rows="1" frameWidth="418" columnsAndRows="1" name="scenery_64" centrePointX="209" centrePointY="185" frameLeft="102" frameHeight="185" columns="1"/><image frameTop="1559" rows="1" frameWidth="334" columnsAndRows="1" name="scenery_65" centrePointX="167" centrePointY="96" frameLeft="440" frameHeight="96" columns="1"/><image frameTop="258" rows="1" frameWidth="197" columnsAndRows="1" name="scenery_66" centrePointX="98.5" centrePointY="189" frameLeft="1829" frameHeight="189" columns="1"/><image frameTop="447" rows="1" frameWidth="160" columnsAndRows="1" name="scenery_67" centrePointX="80" centrePointY="180" frameLeft="1751" frameHeight="180" columns="1"/><image frameTop="1655" rows="1" frameWidth="414" columnsAndRows="1" name="scenery_68" centrePointX="207" centrePointY="145" frameLeft="440" frameHeight="145" columns="1"/><image frameTop="1380" rows="1" frameWidth="508" columnsAndRows="1" name="scenery_69" centrePointX="254" centrePointY="175" frameLeft="531" frameHeight="175" columns="1"/><image frameTop="1555" rows="1" frameWidth="242" columnsAndRows="1" name="scenery_7" centrePointX="121" centrePointY="81" frameLeft="774" frameHeight="81" columns="1"/><image frameTop="1800" rows="1" frameWidth="370" columnsAndRows="1" name="scenery_70" centrePointX="185" centrePointY="131" frameLeft="520" frameHeight="131" columns="1"/><image frameTop="1636" rows="1" frameWidth="164" columnsAndRows="1" name="scenery_71" centrePointX="82" centrePointY="135" frameLeft="854" frameHeight="135" columns="1"/><image frameTop="1771" rows="1" frameWidth="184" columnsAndRows="1" name="scenery_8" centrePointX="92" centrePointY="242" frameLeft="890" frameHeight="242" columns="1"/><image frameTop="1071" rows="1" frameWidth="63" columnsAndRows="1" name="scenery_9" centrePointX="31.5" centrePointY="117" frameLeft="347" frameHeight="117" columns="1"/></root>