<root><image frameTop="0" rows="1" frameWidth="3" columnsAndRows="1" name="Tile_Crablantis0000" centrePointX="0" centrePointY="0" frameLeft="0" frameHeight="3" columns="1"/><image frameTop="3" rows="1" frameWidth="102" columnsAndRows="1" name="Tile_Crablantis0001" centrePointX="0" centrePointY="0" frameLeft="0" frameHeight="102" columns="1"/><image frameTop="105" rows="1" frameWidth="102" columnsAndRows="1" name="Tile_Crablantis0002" centrePointX="0" centrePointY="0" frameLeft="0" frameHeight="102" columns="1"/><image frameTop="207" rows="1" frameWidth="102" columnsAndRows="1" name="Tile_Crablantis0003" centrePointX="0" centrePointY="0" frameLeft="0" frameHeight="102" columns="1"/><image frameTop="309" rows="1" frameWidth="102" columnsAndRows="1" name="Tile_Crablantis0004" centrePointX="0" centrePointY="0" frameLeft="0" frameHeight="102" columns="1"/><image frameTop="411" rows="1" frameWidth="102" columnsAndRows="1" name="Tile_Crablantis0005" centrePointX="0" centrePointY="0" frameLeft="0" frameHeight="102" columns="1"/><image frameTop="513" rows="1" frameWidth="102" columnsAndRows="1" name="Tile_Crablantis0006" centrePointX="0" centrePointY="0" frameLeft="0" frameHeight="102" columns="1"/><image frameTop="615" rows="1" frameWidth="102" columnsAndRows="1" name="Tile_Crablantis0007" centrePointX="0" centrePointY="0" frameLeft="0" frameHeight="102" columns="1"/><image frameTop="717" rows="1" frameWidth="102" columnsAndRows="1" name="Tile_Crablantis0008" centrePointX="0" centrePointY="0" frameLeft="0" frameHeight="102" columns="1"/><image frameTop="819" rows="1" frameWidth="102" columnsAndRows="1" name="Tile_Crablantis0009" centrePointX="0" centrePointY="0" frameLeft="0" frameHeight="102" columns="1"/><image frameTop="921" rows="1" frameWidth="102" columnsAndRows="1" name="Tile_Crablantis0010" centrePointX="0" centrePointY="0" frameLeft="0" frameHeight="102" columns="1"/><image frameTop="1023" rows="1" frameWidth="102" columnsAndRows="1" name="Tile_Crablantis0011" centrePointX="0" centrePointY="0" frameLeft="0" frameHeight="102" columns="1"/><image frameTop="1125" rows="1" frameWidth="102" columnsAndRows="1" name="Tile_Crablantis0012" centrePointX="0" centrePointY="0" frameLeft="0" frameHeight="102" columns="1"/><image frameTop="1227" rows="1" frameWidth="102" columnsAndRows="1" name="Tile_Crablantis0013" centrePointX="0" centrePointY="0" frameLeft="0" frameHeight="102" columns="1"/><image frameTop="1329" rows="1" frameWidth="102" columnsAndRows="1" name="Tile_Crablantis0014" centrePointX="0" centrePointY="0" frameLeft="0" frameHeight="102" columns="1"/><image frameTop="1431" rows="1" frameWidth="102" columnsAndRows="1" name="Tile_Crablantis0015" centrePointX="0" centrePointY="0" frameLeft="0" frameHeight="102" columns="1"/><image frameTop="1533" rows="1" frameWidth="102" columnsAndRows="1" name="Tile_Crablantis0016" centrePointX="0" centrePointY="0" frameLeft="0" frameHeight="102" columns="1"/><image frameTop="1635" rows="1" frameWidth="102" columnsAndRows="1" name="Tile_Crablantis0017" centrePointX="0" centrePointY="0" frameLeft="0" frameHeight="102" columns="1"/><image frameTop="1737" rows="1" frameWidth="102" columnsAndRows="1" name="Tile_Crablantis0018" centrePointX="0" centrePointY="0" frameLeft="0" frameHeight="102" columns="1"/><image frameTop="1839" rows="1" frameWidth="102" columnsAndRows="1" name="Tile_Crablantis0019" centrePointX="0" centrePointY="0" frameLeft="0" frameHeight="102" columns="1"/><image frameTop="1941" rows="1" frameWidth="102" columnsAndRows="1" name="Tile_Crablantis0020" centrePointX="0" centrePointY="0" frameLeft="0" frameHeight="102" columns="1"/><image frameTop="0" rows="1" frameWidth="102" columnsAndRows="1" name="Tile_Crablantis0021" centrePointX="0" centrePointY="0" frameLeft="102" frameHeight="102" columns="1"/><image frameTop="0" rows="1" frameWidth="102" columnsAndRows="1" name="Tile_Crablantis0022" centrePointX="0" centrePointY="0" frameLeft="204" frameHeight="102" columns="1"/><image frameTop="0" rows="1" frameWidth="102" columnsAndRows="1" name="Tile_Crablantis0023" centrePointX="0" centrePointY="0" frameLeft="306" frameHeight="102" columns="1"/><image frameTop="0" rows="1" frameWidth="102" columnsAndRows="1" name="Tile_Crablantis0024" centrePointX="0" centrePointY="0" frameLeft="408" frameHeight="102" columns="1"/><image frameTop="0" rows="1" frameWidth="84" columnsAndRows="1" name="Tile_Slime" centrePointX="0" centrePointY="0" frameLeft="510" frameHeight="84" columns="1"/><image frameTop="0" rows="1" frameWidth="82" columnsAndRows="1" name="Tile_Water" centrePointX="0" centrePointY="0" frameLeft="594" frameHeight="82" columns="1"/><image frameTop="0" rows="1" frameWidth="82" columnsAndRows="1" name="Tile_Water_Top" centrePointX="0" centrePointY="0" frameLeft="676" frameHeight="82" columns="1"/><image frameTop="0" rows="1" frameWidth="146" columnsAndRows="1" name="scenery_1" centrePointX="73" centrePointY="75" frameLeft="758" frameHeight="75" columns="1"/><image frameTop="0" rows="1" frameWidth="536" columnsAndRows="1" name="scenery_18" centrePointX="268" centrePointY="517" frameLeft="904" frameHeight="517" columns="1"/><image frameTop="0" rows="1" frameWidth="463" columnsAndRows="1" name="scenery_19" centrePointX="231.5" centrePointY="493" frameLeft="1440" frameHeight="493" columns="1"/><image frameTop="75" rows="1" frameWidth="100" columnsAndRows="1" name="scenery_2" centrePointX="50" centrePointY="64" frameLeft="758" frameHeight="64" columns="1"/><image frameTop="493" rows="1" frameWidth="287" columnsAndRows="1" name="scenery_20" centrePointX="143.5" centrePointY="229" frameLeft="1440" frameHeight="229" columns="1"/><image frameTop="84" rows="1" frameWidth="173" columnsAndRows="1" name="scenery_21" centrePointX="86.5" centrePointY="593" frameLeft="510" frameHeight="593" columns="1"/><image frameTop="102" rows="1" frameWidth="386" columnsAndRows="1" name="scenery_23" centrePointX="193" centrePointY="696" frameLeft="102" frameHeight="696" columns="1"/><image frameTop="517" rows="1" frameWidth="413" columnsAndRows="1" name="scenery_24" centrePointX="206.5" centrePointY="242" frameLeft="683" frameHeight="242" columns="1"/><image frameTop="139" rows="1" frameWidth="170" columnsAndRows="1" name="scenery_25" centrePointX="85" centrePointY="74" frameLeft="683" frameHeight="74" columns="1"/><image frameTop="722" rows="1" frameWidth="525" columnsAndRows="1" name="scenery_26" centrePointX="262.5" centrePointY="172" frameLeft="1096" frameHeight="172" columns="1"/><image frameTop="493" rows="1" frameWidth="286" columnsAndRows="1" name="scenery_27" centrePointX="143" centrePointY="425" frameLeft="1727" frameHeight="425" columns="1"/><image frameTop="213" rows="1" frameWidth="135" columnsAndRows="1" name="scenery_28" centrePointX="67.5" centrePointY="121" frameLeft="683" frameHeight="121" columns="1"/><image frameTop="334" rows="1" frameWidth="90" columnsAndRows="1" name="scenery_29" centrePointX="45" centrePointY="117" frameLeft="683" frameHeight="117" columns="1"/><image frameTop="759" rows="1" frameWidth="263" columnsAndRows="1" name="scenery_30" centrePointX="131.5" centrePointY="419" frameLeft="488" frameHeight="419" columns="1"/><image frameTop="517" rows="1" frameWidth="208" columnsAndRows="1" name="scenery_31" centrePointX="104" centrePointY="156" frameLeft="1096" frameHeight="156" columns="1"/><image frameTop="451" rows="1" frameWidth="143" columnsAndRows="1" name="scenery_32" centrePointX="71.5" centrePointY="61" frameLeft="683" frameHeight="61" columns="1"/><image frameTop="334" rows="1" frameWidth="98" columnsAndRows="1" name="scenery_33" centrePointX="49" centrePointY="111" frameLeft="773" frameHeight="111" columns="1"/><image frameTop="82" rows="1" frameWidth="46" columnsAndRows="1" name="scenery_34" centrePointX="23" centrePointY="32" frameLeft="683" frameHeight="32" columns="1"/><image frameTop="517" rows="1" frameWidth="131" columnsAndRows="1" name="scenery_35" centrePointX="65.5" centrePointY="147" frameLeft="1304" frameHeight="147" columns="1"/><image frameTop="0" rows="1" frameWidth="125" columnsAndRows="1" name="scenery_36" centrePointX="62.5" centrePointY="147" frameLeft="1903" frameHeight="147" columns="1"/><image frameTop="894" rows="1" frameWidth="434" columnsAndRows="1" name="scenery_37" centrePointX="217" centrePointY="230" frameLeft="751" frameHeight="230" columns="1"/><image frameTop="445" rows="1" frameWidth="65" columnsAndRows="1" name="scenery_38" centrePointX="32.5" centrePointY="33" frameLeft="826" frameHeight="33" columns="1"/><image frameTop="664" rows="1" frameWidth="51" columnsAndRows="1" name="scenery_39" centrePointX="25.5" centrePointY="50" frameLeft="1304" frameHeight="50" columns="1"/><image frameTop="894" rows="1" frameWidth="516" columnsAndRows="1" name="scenery_4" centrePointX="258" centrePointY="859" frameLeft="1185" frameHeight="859" columns="1"/><image frameTop="114" rows="1" frameWidth="47" columnsAndRows="1" name="scenery_40" centrePointX="23.5" centrePointY="22" frameLeft="683" frameHeight="22" columns="1"/><image frameTop="918" rows="1" frameWidth="269" columnsAndRows="1" name="scenery_41" centrePointX="134.5" centrePointY="363" frameLeft="1701" frameHeight="363" columns="1"/><image frameTop="759" rows="1" frameWidth="269" columnsAndRows="1" name="scenery_42" centrePointX="134.5" centrePointY="121" frameLeft="751" frameHeight="121" columns="1"/><image frameTop="1281" rows="1" frameWidth="265" columnsAndRows="1" name="scenery_43" centrePointX="132.5" centrePointY="110" frameLeft="1701" frameHeight="110" columns="1"/><image frameTop="1391" rows="1" frameWidth="288" columnsAndRows="1" name="scenery_44" centrePointX="144" centrePointY="462" frameLeft="1701" frameHeight="462" columns="1"/><image frameTop="673" rows="1" frameWidth="144" columnsAndRows="1" name="scenery_45" centrePointX="72" centrePointY="47" frameLeft="1096" frameHeight="47" columns="1"/><image frameTop="1178" rows="1" frameWidth="469" columnsAndRows="1" name="scenery_46" centrePointX="234.5" centrePointY="517" frameLeft="102" frameHeight="517" columns="1"/><image frameTop="478" rows="1" frameWidth="52" columnsAndRows="1" name="scenery_47" centrePointX="26" centrePointY="26" frameLeft="826" frameHeight="26" columns="1"/><image frameTop="798" rows="1" frameWidth="370" columnsAndRows="1" name="scenery_48" centrePointX="185" centrePointY="378" frameLeft="102" frameHeight="378" columns="1"/><image frameTop="918" rows="1" frameWidth="77" columnsAndRows="1" name="scenery_49" centrePointX="38.5" centrePointY="329" frameLeft="1970" frameHeight="329" columns="1"/><image frameTop="1124" rows="1" frameWidth="304" columnsAndRows="1" name="scenery_50" centrePointX="152" centrePointY="539" frameLeft="751" frameHeight="539" columns="1"/><image frameTop="1695" rows="1" frameWidth="710" columnsAndRows="1" name="scenery_6" centrePointX="355" centrePointY="218" frameLeft="102" frameHeight="218" columns="1"/></root>